dishka_rq/__init__.py
dishka_rq/py.typed
dishka_rq/rq_integration.py
dishka_rq-0.1.1.dist-info/METADATA
dishka_rq-0.1.1.dist-info/WHEEL
dishka_rq-0.1.1.dist-info/licenses/LICENSE
dishka_rq-0.1.1.dist-info/RECORD
