Metadata-Version: 2.4
Name: dishka-rq
Version: 0.1.1
Summary: Dishka integration for RQ.
Project-URL: Source, https://github.com/prepin/dishka-rq
Project-URL: Homepage, https://github.com/prepin/dishka-rq
Project-URL: Documentation, https://github.com/prepin/dishka-rq
Project-URL: Bug Tracker, https://github.com/prepin/dishka-rq/issues
Author-email: Pavel Repin <paul.repin@gmail.com>
License:                                  Apache License
License-File: LICENSE
Classifier: Intended Audience :: Developers
Classifier: License :: OSI Approved :: Apache Software License
Classifier: Operating System :: OS Independent
Classifier: Programming Language :: Python :: 3.10
Classifier: Programming Language :: Python :: 3.11
Classifier: Programming Language :: Python :: 3.12
Classifier: Programming Language :: Python :: 3.13
Classifier: Topic :: Software Development :: Libraries
Classifier: Typing :: Typed
Requires-Python: >=3.10
Requires-Dist: dishka>=1.4.2
Requires-Dist: rq>=2.0.0
